binmanu/__init__.py
binmanu/bintool.py
binmanu/bintool_test.py
binmanu/cbfs_util.py
binmanu/cbfs_util_test.py
binmanu/cmdline.py
binmanu/control.py
binmanu/elf.py
binmanu/elf_test.py
binmanu/entry.py
binmanu/entry_test.py
binmanu/fdt_test.py
binmanu/fip_util.py
binmanu/fip_util_test.py
binmanu/fmap_util.py
binmanu/ftest.py
binmanu/image.py
binmanu/image_test.py
binmanu/main.py
binmanu/setup.py
binmanu/state.py
binmanu/btool/_testing.py
binmanu/btool/btool_gzip.py
binmanu/btool/bzip2.py
binmanu/btool/cbfstool.py
binmanu/btool/fiptool.py
binmanu/btool/futility.py
binmanu/btool/ifwitool.py
binmanu/btool/lz4.py
binmanu/btool/lzma_alone.py
binmanu/btool/lzop.py
binmanu/btool/mkimage.py
binmanu/btool/xz.py
binmanu/btool/zstd.py
binmanu/etype/_testing.py
binmanu/etype/atf_bl31.py
binmanu/etype/atf_fip.py
binmanu/etype/blob.py
binmanu/etype/blob_dtb.py
binmanu/etype/blob_ext.py
binmanu/etype/blob_ext_list.py
binmanu/etype/blob_named_by_arg.py
binmanu/etype/blob_phase.py
binmanu/etype/cbfs.py
binmanu/etype/collection.py
binmanu/etype/cros_ec_rw.py
binmanu/etype/fdtmap.py
binmanu/etype/files.py
binmanu/etype/fill.py
binmanu/etype/fit.py
binmanu/etype/fmap.py
binmanu/etype/gbb.py
binmanu/etype/image_header.py
binmanu/etype/intel_cmc.py
binmanu/etype/intel_descriptor.py
binmanu/etype/intel_fit.py
binmanu/etype/intel_fit_ptr.py
binmanu/etype/intel_fsp.py
binmanu/etype/intel_fsp_m.py
binmanu/etype/intel_fsp_s.py
binmanu/etype/intel_fsp_t.py
binmanu/etype/intel_ifwi.py
binmanu/etype/intel_me.py
binmanu/etype/intel_mrc.py
binmanu/etype/intel_refcode.py
binmanu/etype/intel_vbt.py
binmanu/etype/intel_vga.py
binmanu/etype/mkimage.py
binmanu/etype/null.py
binmanu/etype/opensbi.py
binmanu/etype/powerpc_mpc85xx_bootpg_resetvec.py
binmanu/etype/pre_load.py
binmanu/etype/scp.py
binmanu/etype/section.py
binmanu/etype/tee_os.py
binmanu/etype/text.py
binmanu/etype/u_boot.py
binmanu/etype/u_boot_dtb.py
binmanu/etype/u_boot_dtb_with_ucode.py
binmanu/etype/u_boot_elf.py
binmanu-0.0.1.dist-info/LICENSE
binmanu-0.0.1.dist-info/METADATA
binmanu-0.0.1.dist-info/WHEEL
binmanu-0.0.1.dist-info/entry_points.txt
binmanu-0.0.1.dist-info/top_level.txt
binmanu-0.0.1.dist-info/RECORD
